{
  "GAS": {
    "NATURGY": {
      "tarifaType": "GAS",
      "metadata": {
        "comercializadora": "NATURGY",
        "ultimaActualizacion": "2026-05-26"
      },
      "productos": [
        {
          "band": "RL1",
          "nombre": "Tarifa Por Uso RL1",
          "terminoFijoDiario": 0.080382,
          "terminoVariableKwh": 0.072843
        },
        {
          "band": "RL2",
          "nombre": "Tarifa Por Uso RL2",
          "terminoFijoDiario": 0.211856,
          "terminoVariableKwh": 0.070744
        },
        {
          "band": "RL3",
          "nombre": "Tarifa Por Uso RL3",
          "terminoFijoDiario": 0.560676,
          "terminoVariableKwh": 0.067304
        }
      ]
    },
    "ENDESA": {
      "tarifaType": "GAS",
      "metadata": {
        "comercializadora": "ENDESA"
      },
      "productos": [
        {
          "band": "RL1",
          "nombre": "GAS ENDESA RL1 PDS",
          "terminoFijoDiario": 0.23608767,
          "terminoVariableKwh": 0.0847
        },
        {
          "band": "RL2",
          "nombre": "GAS ENDESA RL2 PDS",
          "terminoFijoDiario": 0.48,
          "terminoVariableKwh": 0.0802
        },
        {
          "band": "RL3",
          "nombre": "GAS ENDESA RL3 PDS",
          "terminoFijoDiario": 1.01675,
          "terminoVariableKwh": 0.074
        }
      ]
    },
    "REPSOL": {
      "tarifaType": "GAS",
      "metadata": {
        "comercializadora": "REPSOL"
      },
      "productos": [
        {
          "band": "RL1",
          "nombre": "RL1 GAS 12M V11 REPSOL",
          "terminoFijoDiario": 0.0699,
          "terminoVariableKwh": 0.0648,
          "activo": false
        },
        {
          "band": "RL1",
          "nombre": "RL1 GAS 12M V12 REPSOL",
          "terminoFijoDiario": 0.0659,
          "terminoVariableKwh": 0.0648,
          "activo": false
        },
        {
          "band": "RL2",
          "nombre": "RL2 GAS 12M MV REPSOL",
          "terminoFijoDiario": 0.363333,
          "terminoVariableKwh": 0.0899,
          "activo": false
        },
        {
          "band": "RL3",
          "nombre": "RL3 GAS 12M MV REPSOL",
          "terminoFijoDiario": 0.363333,
          "terminoVariableKwh": 0.0899,
          "activo": false
        }
      ]
    },
    "ELEIA": {
      "tarifaType": "GAS",
      "metadata": {
        "comercializadora": "ELEIA",
        "ultimaActualizacion": "2026-06-17"
      },
      "productos": [
        {
          "band": "RL1",
          "nombre": "TDE3 RL1",
          "terminoFijoDiario": 0.14103333,
          "terminoVariableKwh": 0.060685
        },
        {
          "band": "RL1",
          "nombre": "TDE2 RL1",
          "terminoFijoDiario": 0.19103333,
          "terminoVariableKwh": 0.066685
        },
        {
          "band": "RL1",
          "nombre": "TDE1 RL1",
          "terminoFijoDiario": 0.26103333,
          "terminoVariableKwh": 0.072685
        },
        {
          "band": "RL1",
          "nombre": "TDE0 RL1",
          "terminoFijoDiario": 0.27436667,
          "terminoVariableKwh": 0.078685
        },
        {
          "band": "RL2",
          "nombre": "TDE3 RL2",
          "terminoFijoDiario": 0.26696667,
          "terminoVariableKwh": 0.055685
        },
        {
          "band": "RL2",
          "nombre": "TDE2 RL2",
          "terminoFijoDiario": 0.3003,
          "terminoVariableKwh": 0.061685
        },
        {
          "band": "RL2",
          "nombre": "TDE1 RL2",
          "terminoFijoDiario": 0.36696667,
          "terminoVariableKwh": 0.067685
        },
        {
          "band": "RL2",
          "nombre": "TDE0 RL2",
          "terminoFijoDiario": 0.3703,
          "terminoVariableKwh": 0.073685
        },
        {
          "band": "RL3",
          "nombre": "TDE3 RL3",
          "terminoFijoDiario": 0.5852,
          "terminoVariableKwh": 0.054685
        },
        {
          "band": "RL3",
          "nombre": "TDE2 RL3",
          "terminoFijoDiario": 0.61853333,
          "terminoVariableKwh": 0.060685
        },
        {
          "band": "RL3",
          "nombre": "TDE1 RL3",
          "terminoFijoDiario": 0.6852,
          "terminoVariableKwh": 0.066685
        },
        {
          "band": "RL3",
          "nombre": "TDE0 RL3",
          "terminoFijoDiario": 0.68853333,
          "terminoVariableKwh": 0.072685
        },
        {
          "band": "RL4",
          "nombre": "TDE3 RL4",
          "terminoFijoDiario": 1.3841,
          "terminoVariableKwh": 0.052085
        },
        {
          "band": "RL4",
          "nombre": "TDE2 RL4",
          "terminoFijoDiario": 1.40076667,
          "terminoVariableKwh": 0.057085
        },
        {
          "band": "RL4",
          "nombre": "TDE1 RL4",
          "terminoFijoDiario": 1.4341,
          "terminoVariableKwh": 0.063085
        },
        {
          "band": "RL4",
          "nombre": "TDE0 RL4",
          "terminoFijoDiario": 1.46743333,
          "terminoVariableKwh": 0.068085
        },
        {
          "band": "RL5",
          "nombre": "TDE3 RL5",
          "terminoFijoDiario": 7.6483,
          "terminoVariableKwh": 0.051685
        },
        {
          "band": "RL5",
          "nombre": "TDE2 RL5",
          "terminoFijoDiario": 7.66496667,
          "terminoVariableKwh": 0.055685
        },
        {
          "band": "RL5",
          "nombre": "TDE1 RL5",
          "terminoFijoDiario": 7.6983,
          "terminoVariableKwh": 0.060685
        },
        {
          "band": "RL5",
          "nombre": "TDE0 RL5",
          "terminoFijoDiario": 7.73163333,
          "terminoVariableKwh": 0.065685
        },
        {
          "band": "RL1",
          "nombre": "TEE3 RL1",
          "terminoFijoDiario": 0.07436667,
          "terminoVariableKwh": 0.060685
        },
        {
          "band": "RL1",
          "nombre": "TEE2 RL1",
          "terminoFijoDiario": 0.07436667,
          "terminoVariableKwh": 0.066685
        },
        {
          "band": "RL1",
          "nombre": "TEE1 RL1",
          "terminoFijoDiario": 0.07436667,
          "terminoVariableKwh": 0.072685
        },
        {
          "band": "RL1",
          "nombre": "TEE0 RL1",
          "terminoFijoDiario": 0.07436667,
          "terminoVariableKwh": 0.078685
        },
        {
          "band": "RL2",
          "nombre": "TEE3 RL2",
          "terminoFijoDiario": 0.19363333,
          "terminoVariableKwh": 0.055685
        },
        {
          "band": "RL2",
          "nombre": "TEE2 RL2",
          "terminoFijoDiario": 0.19363333,
          "terminoVariableKwh": 0.061685
        },
        {
          "band": "RL2",
          "nombre": "TEE1 RL2",
          "terminoFijoDiario": 0.19363333,
          "terminoVariableKwh": 0.067685
        },
        {
          "band": "RL2",
          "nombre": "TEE0 RL2",
          "terminoFijoDiario": 0.19363333,
          "terminoVariableKwh": 0.073685
        },
        {
          "band": "RL3",
          "nombre": "TEE3 RL3",
          "terminoFijoDiario": 0.51186667,
          "terminoVariableKwh": 0.054685
        },
        {
          "band": "RL3",
          "nombre": "TEE2 RL3",
          "terminoFijoDiario": 0.51186667,
          "terminoVariableKwh": 0.060685
        },
        {
          "band": "RL3",
          "nombre": "TEE1 RL3",
          "terminoFijoDiario": 0.51186667,
          "terminoVariableKwh": 0.066685
        },
        {
          "band": "RL3",
          "nombre": "TEE0 RL3",
          "terminoFijoDiario": 0.51186667,
          "terminoVariableKwh": 0.072685
        },
        {
          "band": "RL4",
          "nombre": "TEE3 RL4",
          "terminoFijoDiario": 1.36743333,
          "terminoVariableKwh": 0.052085
        },
        {
          "band": "RL4",
          "nombre": "TEE2 RL4",
          "terminoFijoDiario": 1.36743333,
          "terminoVariableKwh": 0.057085
        },
        {
          "band": "RL4",
          "nombre": "TEE1 RL4",
          "terminoFijoDiario": 1.36743333,
          "terminoVariableKwh": 0.063085
        },
        {
          "band": "RL4",
          "nombre": "TEE0 RL4",
          "terminoFijoDiario": 1.36743333,
          "terminoVariableKwh": 0.068085
        },
        {
          "band": "RL5",
          "nombre": "TEE3 RL5",
          "terminoFijoDiario": 7.63163333,
          "terminoVariableKwh": 0.051685
        },
        {
          "band": "RL5",
          "nombre": "TEE2 RL5",
          "terminoFijoDiario": 7.63163333,
          "terminoVariableKwh": 0.055685
        },
        {
          "band": "RL5",
          "nombre": "TEE1 RL5",
          "terminoFijoDiario": 7.63163333,
          "terminoVariableKwh": 0.060685
        },
        {
          "band": "RL5",
          "nombre": "TEE0 RL5",
          "terminoFijoDiario": 7.63163333,
          "terminoVariableKwh": 0.065685
        }
      ]
    },
    "TOTAL ENERGIES": {
      "tarifaType": "GAS",
      "metadata": {
        "comercializadora": "TOTAL ENERGIES",
        "ultimaActualizacion": "2026-06-16"
      },
      "productos": [
        {
          "band": "RL1",
          "nombre": "CLASICA TG1",
          "terminoFijoDiario": 0.17196521,
          "terminoVariableKwh": 0.075647
        },
        {
          "band": "RL2",
          "nombre": "CLASICA TG1",
          "terminoFijoDiario": 0.28962356,
          "terminoVariableKwh": 0.073579
        },
        {
          "band": "RL3",
          "nombre": "CLASICA TG1",
          "terminoFijoDiario": 0.60347041,
          "terminoVariableKwh": 0.068189
        },
        {
          "band": "RL4",
          "nombre": "CLASICA TG1",
          "terminoFijoDiario": 1.41446082,
          "terminoVariableKwh": 0.070294
        },
        {
          "band": "RL5",
          "nombre": "CLASICA TG1 AP",
          "terminoFijoDiario": 7.55995096,
          "terminoVariableKwh": 0.069653
        },
        {
          "band": "RL5",
          "nombre": "CLASICA TG1 BP",
          "terminoFijoDiario": 7.55995096,
          "terminoVariableKwh": 0.070232
        },
        {
          "band": "RL1",
          "nombre": "CLASICA TG2",
          "terminoFijoDiario": 0.23771863,
          "terminoVariableKwh": 0.077647
        },
        {
          "band": "RL2",
          "nombre": "CLASICA TG2",
          "terminoFijoDiario": 0.35537699,
          "terminoVariableKwh": 0.075579
        },
        {
          "band": "RL3",
          "nombre": "CLASICA TG2",
          "terminoFijoDiario": 0.66922384,
          "terminoVariableKwh": 0.070189
        },
        {
          "band": "RL4",
          "nombre": "CLASICA TG2",
          "terminoFijoDiario": 1.50322795,
          "terminoVariableKwh": 0.072794
        },
        {
          "band": "RL5",
          "nombre": "CLASICA TG2 AP",
          "terminoFijoDiario": 7.58296466,
          "terminoVariableKwh": 0.071153
        },
        {
          "band": "RL5",
          "nombre": "CLASICA TG2 BP",
          "terminoFijoDiario": 7.58296466,
          "terminoVariableKwh": 0.071732
        },
        {
          "band": "RL1",
          "nombre": "CLASICA TG3",
          "terminoFijoDiario": 0.27059534,
          "terminoVariableKwh": 0.079647
        },
        {
          "band": "RL2",
          "nombre": "CLASICA TG3",
          "terminoFijoDiario": 0.3882537,
          "terminoVariableKwh": 0.077579
        },
        {
          "band": "RL3",
          "nombre": "CLASICA TG3",
          "terminoFijoDiario": 0.70210055,
          "terminoVariableKwh": 0.072189
        },
        {
          "band": "RL4",
          "nombre": "CLASICA TG3",
          "terminoFijoDiario": 1.51309096,
          "terminoVariableKwh": 0.074794
        },
        {
          "band": "RL5",
          "nombre": "CLASICA TG3 AP",
          "terminoFijoDiario": 7.60926603,
          "terminoVariableKwh": 0.073153
        },
        {
          "band": "RL5",
          "nombre": "CLASICA TG3 BP",
          "terminoFijoDiario": 7.60926603,
          "terminoVariableKwh": 0.073732
        },
        {
          "band": "RL1",
          "nombre": "CLASICA TG4",
          "terminoFijoDiario": 0.33634877,
          "terminoVariableKwh": 0.082647
        },
        {
          "band": "RL2",
          "nombre": "CLASICA TG4",
          "terminoFijoDiario": 0.45400712,
          "terminoVariableKwh": 0.080579
        },
        {
          "band": "RL3",
          "nombre": "CLASICA TG4",
          "terminoFijoDiario": 0.73497726,
          "terminoVariableKwh": 0.075189
        },
        {
          "band": "RL4",
          "nombre": "CLASICA TG4",
          "terminoFijoDiario": 1.56240603,
          "terminoVariableKwh": 0.077294
        },
        {
          "band": "RL5",
          "nombre": "CLASICA TG4 AP",
          "terminoFijoDiario": 7.67501945,
          "terminoVariableKwh": 0.075653
        },
        {
          "band": "RL5",
          "nombre": "CLASICA TG4 BP",
          "terminoFijoDiario": 7.67501945,
          "terminoVariableKwh": 0.076232
        },
        {
          "band": "RL1",
          "nombre": "CLASICA TG5",
          "terminoFijoDiario": 0.73086932,
          "terminoVariableKwh": 0.089647
        },
        {
          "band": "RL2",
          "nombre": "CLASICA TG5",
          "terminoFijoDiario": 0.84852767,
          "terminoVariableKwh": 0.087579
        },
        {
          "band": "RL3",
          "nombre": "CLASICA TG5",
          "terminoFijoDiario": 1.16237452,
          "terminoVariableKwh": 0.082189
        },
        {
          "band": "RL4",
          "nombre": "CLASICA TG5",
          "terminoFijoDiario": 2.00624164,
          "terminoVariableKwh": 0.085294
        },
        {
          "band": "RL5",
          "nombre": "CLASICA TG5 AP",
          "terminoFijoDiario": 8.18460849,
          "terminoVariableKwh": 0.079653
        },
        {
          "band": "RL5",
          "nombre": "CLASICA TG5 BP",
          "terminoFijoDiario": 8.18460849,
          "terminoVariableKwh": 0.080232
        }
      ]
    },
    "TOTAL RESIDENCIAL": {
      "tarifaType": "GAS",
      "metadata": {
        "comercializadora": "TOTAL RESIDENCIAL",
        "ultimaActualizacion": "2026-04-15"
      },
      "productos": [
        {
          "band": "RL1",
          "nombre": "A TU AIRE GAS",
          "terminoFijoDiario": 0.312329,
          "terminoVariableKwh": 0.073
        },
        {
          "band": "RL2",
          "nombre": "A TU AIRE GAS",
          "terminoFijoDiario": 0.476712,
          "terminoVariableKwh": 0.071
        },
        {
          "band": "RL3",
          "nombre": "A TU AIRE GAS",
          "terminoFijoDiario": 0.805479,
          "terminoVariableKwh": 0.069
        }
      ]
    },
    "LOGOS": {
      "tarifaType": "GAS",
      "metadata": {
        "comercializadora": "LOGOS"
      },
      "productos": [
        {
          "band": "RL1",
          "nombre": "FIJO HOGAR EPSILON",
          "terminoFijoDiario": 0.23769863,
          "terminoVariableKwh": 0.086294,
          "activo": true
        },
        {
          "band": "RL2",
          "nombre": "FIJO HOGAR EPSILON",
          "terminoFijoDiario": 0.35539726,
          "terminoVariableKwh": 0.080976,
          "activo": true
        },
        {
          "band": "RL3",
          "nombre": "FIJO HOGAR EPSILON",
          "terminoFijoDiario": 0.66936986,
          "terminoVariableKwh": 0.077586,
          "activo": true
        },
        {
          "band": "RL1",
          "nombre": "FIJO HOGAR DELTA",
          "terminoFijoDiario": 0.23769863,
          "terminoVariableKwh": 0.082842,
          "activo": true
        },
        {
          "band": "RL2",
          "nombre": "FIJO HOGAR DELTA",
          "terminoFijoDiario": 0.35539726,
          "terminoVariableKwh": 0.077737,
          "activo": true
        },
        {
          "band": "RL3",
          "nombre": "FIJO HOGAR DELTA",
          "terminoFijoDiario": 0.66936986,
          "terminoVariableKwh": 0.074482,
          "activo": true
        },
        {
          "band": "RL1",
          "nombre": "FIJO HOGAR BETA",
          "terminoFijoDiario": 0.23769863,
          "terminoVariableKwh": 0.080253,
          "activo": true
        },
        {
          "band": "RL2",
          "nombre": "FIJO HOGAR BETA",
          "terminoFijoDiario": 0.35539726,
          "terminoVariableKwh": 0.075307,
          "activo": true
        },
        {
          "band": "RL3",
          "nombre": "FIJO HOGAR BETA",
          "terminoFijoDiario": 0.66936986,
          "terminoVariableKwh": 0.072155,
          "activo": true
        },
        {
          "band": "RL1",
          "nombre": "FIJO PYME EPSILON",
          "terminoFijoDiario": 0.23769863,
          "terminoVariableKwh": 0.077794,
          "activo": true
        },
        {
          "band": "RL2",
          "nombre": "FIJO PYME EPSILON",
          "terminoFijoDiario": 0.35539726,
          "terminoVariableKwh": 0.075726,
          "activo": true
        },
        {
          "band": "RL3",
          "nombre": "FIJO PYME EPSILON",
          "terminoFijoDiario": 0.66936986,
          "terminoVariableKwh": 0.072336,
          "activo": true
        },
        {
          "band": "RL4",
          "nombre": "FIJO PYME EPSILON",
          "terminoFijoDiario": 1.5129863,
          "terminoVariableKwh": 0.070441,
          "activo": true
        },
        {
          "band": "RL1",
          "nombre": "FIJO PYME DELTA",
          "terminoFijoDiario": 0.23769863,
          "terminoVariableKwh": 0.074294,
          "activo": true
        },
        {
          "band": "RL2",
          "nombre": "FIJO PYME DELTA",
          "terminoFijoDiario": 0.35539726,
          "terminoVariableKwh": 0.072226,
          "activo": true
        },
        {
          "band": "RL3",
          "nombre": "FIJO PYME DELTA",
          "terminoFijoDiario": 0.66936986,
          "terminoVariableKwh": 0.068836,
          "activo": true
        },
        {
          "band": "RL4",
          "nombre": "FIJO PYME DELTA",
          "terminoFijoDiario": 1.5129863,
          "terminoVariableKwh": 0.067941,
          "activo": true
        },
        {
          "band": "RL1",
          "nombre": "FIJO PYME GAMMA",
          "terminoFijoDiario": 0.17194521,
          "terminoVariableKwh": 0.072294,
          "activo": true
        },
        {
          "band": "RL2",
          "nombre": "FIJO PYME GAMMA",
          "terminoFijoDiario": 0.28964384,
          "terminoVariableKwh": 0.070226,
          "activo": true
        },
        {
          "band": "RL3",
          "nombre": "FIJO PYME GAMMA",
          "terminoFijoDiario": 0.60361644,
          "terminoVariableKwh": 0.066836,
          "activo": true
        },
        {
          "band": "RL4",
          "nombre": "FIJO PYME GAMMA",
          "terminoFijoDiario": 1.44723288,
          "terminoVariableKwh": 0.065941,
          "activo": true
        },
        {
          "band": "RL1",
          "nombre": "FIJO PYME BETA",
          "terminoFijoDiario": 0.17194521,
          "terminoVariableKwh": 0.068794,
          "activo": true
        },
        {
          "band": "RL2",
          "nombre": "FIJO PYME BETA",
          "terminoFijoDiario": 0.28964384,
          "terminoVariableKwh": 0.066726,
          "activo": true
        },
        {
          "band": "RL3",
          "nombre": "FIJO PYME BETA",
          "terminoFijoDiario": 0.60361644,
          "terminoVariableKwh": 0.063336,
          "activo": true
        },
        {
          "band": "RL4",
          "nombre": "FIJO PYME BETA",
          "terminoFijoDiario": 1.44723288,
          "terminoVariableKwh": 0.062941,
          "activo": true
        },
        {
          "band": "RL1",
          "nombre": "FIJO PYME ALFA",
          "terminoFijoDiario": 0.07331507,
          "terminoVariableKwh": 0.066294,
          "activo": true
        },
        {
          "band": "RL2",
          "nombre": "FIJO PYME ALFA",
          "terminoFijoDiario": 0.1910137,
          "terminoVariableKwh": 0.064226,
          "activo": true
        },
        {
          "band": "RL3",
          "nombre": "FIJO PYME ALFA",
          "terminoFijoDiario": 0.5049863,
          "terminoVariableKwh": 0.060836,
          "activo": true
        },
        {
          "band": "RL4",
          "nombre": "FIJO PYME ALFA",
          "terminoFijoDiario": 1.34860274,
          "terminoVariableKwh": 0.060941,
          "activo": true
        },
        {
          "band": "RL5",
          "nombre": "FIJO PYME ALFA",
          "terminoFijoDiario": 7.52712329,
          "terminoVariableKwh": 0.060879,
          "activo": true
        }
      ]
    }
  }
}
